<pkgdesc name='libIDL' version='0.8.13'>
    <subpackage name='skel'/>
    <subpackage name='minimal'>
        <file group='0' mode='100755' path='/usr/lib/libIDL-2.so.0.0.0' owner='0'/>
    </subpackage>
    <subpackage name='bin'/>
    <subpackage name='doc'>
        <file group='0' mode='100644' path='/usr/share/info/dir' owner='0'/>
        <file group='0' mode='100644' path='/usr/share/info/libIDL2.info' owner='0'/>
    </subpackage>
    <subpackage name='config'/>
    <subpackage name='devel'>
        <file group='0' mode='100755' path='/usr/bin/libIDL-config-2' owner='0'/>
        <file group='0' mode='100644' path='/usr/include/libIDL-2.0/libIDL/IDL.h' owner='0'/>
        <file group='0' mode='100644' path='/usr/lib/libIDL-2.a' owner='0'/>
        <file group='0' mode='100644' path='/usr/lib/pkgconfig/libIDL-2.0.pc' owner='0'/>
        <file group='0' mode='100755' path='/usr/lib/libIDL-2.la' owner='0'/>
    </subpackage>
    <subpackage name='localization'/>
    <subpackage name='tzdata'/>
    <subpackage name='uncategorized'/>
    <subpackage name='ignore'/>
    <vanished>
        <subpackage name='config'/>
        <subpackage name='doc'/>
        <subpackage name='minimal'/>
        <subpackage name='devel'/>
        <subpackage name='localization'/>
        <subpackage name='bin'/>
        <subpackage name='ignore'/>
        <subpackage name='uncategorized'/>
        <subpackage name='tzdata'/>
        <subpackage name='skel'/>
    </vanished>
</pkgdesc>